{
    "prepare_queue": {
        "installed": [],
        "uninstalled": []
    },
    "config_munge": {
        "files": {}
    },
    "installed_plugins": {
        "cordova-plugin-whitelist": {
            "PACKAGE_NAME": "ca.tempstars.app"
        },
        "cordova-plugin-device": {
            "PACKAGE_NAME": "ca.tempstars.app"
        },
        "cordova-plugin-splashscreen": {
            "PACKAGE_NAME": "ca.tempstars.app"
        },
        "cordova-plugin-network-information": {
            "PACKAGE_NAME": "ca.tempstars.app"
        },
        "cordova-plugin-geolocation": {
            "PACKAGE_NAME": "ca.tempstars.app"
        },
        "cordova-plugin-console": {
            "PACKAGE_NAME": "ca.tempstars.app"
        },
        "cordova-plugin-file-transfer": {
            "PACKAGE_NAME": "ca.tempstars.app"
        },
        "ionic-plugin-keyboard": {
            "PACKAGE_NAME": "ca.tempstars.app"
        },
        "cordova-plugin-nativestorage": {
            "PACKAGE_NAME": "ca.tempstars.app2"
        },
        "cordova-plugin-inappbrowser": {
            "PACKAGE_NAME": "ca.tempstars.app2"
        },
        "phonegap-plugin-push": {
            "SENDER_ID": "210360814619",
            "PACKAGE_NAME": "ca.tempstars.app2"
        }
    },
    "dependent_plugins": {
        "cordova-plugin-compat": {
            "PACKAGE_NAME": "ca.tempstars.app"
        },
        "cordova-plugin-file": {
            "PACKAGE_NAME": "ca.tempstars.app"
        }
    }
}