{
  "name": "Region",
  "base": "PersistedModel",
  "options": {
    "idInjection": false,
    "mysql": {
      "schema": "tempstars",
      "table": "Region"
    }
  },
  "properties": {
    "id": {
      "type": "Number",
      "id": true,
      "generated": true,
      "required": true,
      "length": null,
      "precision": 10,
      "scale": 0,
      "mysql": {
        "columnName": "id",
        "dataType": "int",
        "dataLength": null,
        "dataPrecision": 10,
        "dataScale": 0,
        "nullable": "N"
      }
    },
    "description": {
      "type": "String",
      "required": true,
      "length": 50,
      "precision": null,
      "scale": null,
      "mysql": {
        "columnName": "description",
        "dataType": "varchar",
        "dataLength": 50,
        "dataPrecision": null,
        "dataScale": null,
        "nullable": "N"
      }
    },
    "rate": {
      "type": "String",
      "required": true,
      "length": null,
      "precision": 6,
      "scale": 2,
      "mysql": {
        "columnName": "rate",
        "dataType": "decimal",
        "dataLength": null,
        "dataPrecision": 6,
        "dataScale": 2,
        "nullable": "N"
      }
    }
  },
  "validations": [],
  "relations": {
    "postalCodes": {
      "type": "hasMany",
      "model": "PostalCode",
      "foreignKey": ""
    },
    "dentist": {
      "type": "hasMany",
      "model": "Dentist",
      "foreignKey": "regionId"
    },
    "hygienist": {
      "type": "hasMany",
      "model": "Hygienist",
      "foreignKey": "regionId"
    }
  },
  "acls": [],
  "methods": {}
}
